{
  "docusaurus-plugin-content-docs": {
    "default": {
      "path": "/bar1-s2-docs/fr/docs",
      "versions": [
        {
          "name": "current",
          "label": "Next",
          "isLast": true,
          "path": "/bar1-s2-docs/fr/docs",
          "mainDocId": "overview",
          "docs": [
            {
              "id": "intro",
              "path": "/bar1-s2-docs/fr/docs/intro",
              "sidebar": "tutorialSidebar"
            },
            {
              "id": "overview",
              "path": "/bar1-s2-docs/fr/docs/overview",
              "sidebar": "tutorialSidebar"
            }
          ],
          "draftIds": [],
          "sidebars": {
            "tutorialSidebar": {
              "link": {
                "path": "/bar1-s2-docs/fr/docs/overview",
                "label": "overview"
              }
            }
          }
        }
      ],
      "breadcrumbs": true
    }
  }
}